dir/PIL2CV.py
dir/filetypeDetector.py
dir/imageConverter.py
dir/preprocess.py
ocr_pdf_jpg_png-0.9.0.dist-info/entry_points.txt
ocr_pdf_jpg_png-0.9.0.dist-info/LICENSE.md
ocr_pdf_jpg_png-0.9.0.dist-info/WHEEL
ocr_pdf_jpg_png-0.9.0.dist-info/METADATA
ocr_pdf_jpg_png-0.9.0.dist-info/RECORD
